gpsoauth_compat/__init__.py
gpsoauth_compat/credentials.py
gpsoauth_compat/flow.py
gpsoauth_compat-0.1.0rc1.dist-info/LICENSE
gpsoauth_compat-0.1.0rc1.dist-info/METADATA
gpsoauth_compat-0.1.0rc1.dist-info/WHEEL
gpsoauth_compat-0.1.0rc1.dist-info/RECORD
