Metadata-Version: 2.3
Name: gpsoauth-compat
Version: 0.1.0rc1
Summary: gpsoauth compatibility layer for google-api-python-client
Author: Youssef Samy
Author-email: office.youssefkassem@gmail.com
Requires-Python: >=3.9,<4
Classifier: Programming Language :: Python :: 3
Classifier: Programming Language :: Python :: 3.9
Classifier: Programming Language :: Python :: 3.10
Classifier: Programming Language :: Python :: 3.11
Classifier: Programming Language :: Python :: 3.12
Classifier: Programming Language :: Python :: 3.13
Requires-Dist: google-auth
Requires-Dist: gpsoauth (>=1.1.1)
Requires-Dist: poetry-core (>=2.0.0,<3.0.0)
